[{"id":"grandmother"},{"id":"pixie"},{"id":"balloonist"},{"id":"general"},{"id":"dreamer"},{"id":"gossip"},{"id":"cannibal"},{"id":"philosopher"},{"id":"amnesiac"},{"id":"magician"},{"id":"farmer"},{"id":"poppy_grower"},{"id":"pacifist"},{"id":"acrobat"},{"id":"drunk"},{"id":"politician"},{"id":"sweetheart"},{"id":"mephit"},{"id":"poisoner"},{"id":"devils_advocate"},{"id":"marionette"},{"id":"lleech"},{"id":"lil_monsta"},{"id":"no_dashii"},{"id":"vigormortis"},{"id":"gangster"},{"id":"sentinel"}]